gymnasium_retinatask/__init__.py
gymnasium_retinatask/retina_env.py
gymnasium_retinatask/examples/__init__.py
gymnasium_retinatask/examples/pattern_analysis.py
gymnasium_retinatask/examples/perfect_agent.py
gymnasium_retinatask/examples/random_agent.py
gymnasium_retinatask/tests/__init__.py
gymnasium_retinatask/tests/test_retina_env.py
gymnasium_retinatask-0.1.0.dist-info/licenses/LICENSE
gymnasium_retinatask-0.1.0.dist-info/METADATA
gymnasium_retinatask-0.1.0.dist-info/WHEEL
gymnasium_retinatask-0.1.0.dist-info/top_level.txt
gymnasium_retinatask-0.1.0.dist-info/RECORD
