Metadata-Version: 2.4
Name: gymnasium-retinatask
Version: 0.1.0
Summary: A Gymnasium-compatible implementation of the Left & Right Retina Problem
Author-email: Stefano Palmieri <teaspoonaistu@gmail.com>
License-Expression: MIT
Project-URL: Homepage, https://github.com/Teaspoon-AI/gymnasium-retinatask
Project-URL: Bug Tracker, https://github.com/Teaspoon-AI/gymnasium-retinatask/issues
Classifier: Programming Language :: Python :: 3
Classifier: Programming Language :: Python :: 3.10
Classifier: Programming Language :: Python :: 3.11
Classifier: Programming Language :: Python :: 3.12
Classifier: Programming Language :: Python :: 3.13
Classifier: Operating System :: OS Independent
Classifier: Topic :: Scientific/Engineering :: Artificial Intelligence
Requires-Python: >=3.10
License-File: LICENSE
Requires-Dist: gymnasium>=1.1.1
Requires-Dist: numpy>=1.21.0
Dynamic: license-file
